[
  {
    "SongID": 1274271,
    "Position": 1
  },
  {
    "SongID": 1292148,
    "Position": 2
  },
  {
    "SongID": 1274806514,
    "Position": 3
  },
  {
    "SongID": 1274802545,
    "Position": 4
  },
  {
    "SongID": 1274741,
    "Position": 5
  },
  {
    "SongID": 1274799549,
    "Position": 6
  },
  {
    "SongID": 1288682,
    "Position": 8
  },
  {
    "SongID": 1274799562,
    "Position": 9
  },
  {
    "SongID": 1288726,
    "Position": 10
  },
  {
    "SongID": 1274729,
    "Position": 11
  },
  {
    "SongID": 1274806787,
    "Position": 12
  },
  {
    "SongID": 3263,
    "Position": 13
  },
  {
    "SongID": 1295927,
    "Position": 14
  },
  {
    "SongID": 612111,
    "Position": 15
  },
  {
    "SongID": 1274806517,
    "Position": 16
  },
  {
    "SongID": 1278109,
    "Position": 17
  },
  {
    "SongID": 1274799551,
    "Position": 18
  },
  {
    "SongID": 1289912,
    "Position": 19
  },
  {
    "SongID": 1289911,
    "Position": 20
  },
  {
    "SongID": 1274806518,
    "Position": 21
  },
  {
    "SongID": 1274806776,
    "Position": 22
  },
  {
    "SongID": 803855,
    "Position": 23
  },
  {
    "SongID": 1274799553,
    "Position": 24
  },
  {
    "SongID": 1274803150,
    "Position": 25
  },
  {
    "SongID": 1274806778,
    "Position": 26
  },
  {
    "SongID": 1274806777,
    "Position": 27
  },
  {
    "SongID": 1274757,
    "Position": 28
  },
  {
    "SongID": 1274806779,
    "Position": 29
  },
  {
    "SongID": 1274799558,
    "Position": 30
  },
  {
    "SongID": 1274806780,
    "Position": 31
  },
  {
    "SongID": 1274820493,
    "Position": 32
  },
  {
    "SongID": 1274809037,
    "Position": 33
  },
  {
    "SongID": 1274733,
    "Position": 34
  },
  {
    "SongID": 5480,
    "Position": 35
  },
  {
    "SongID": 1274799552,
    "Position": 37
  },
  {
    "SongID": 1274803148,
    "Position": 38
  },
  {
    "SongID": 1274804244,
    "Position": 39
  },
  {
    "SongID": 1274736,
    "Position": 40
  },
  {
    "SongID": 1274724,
    "Position": 42
  },
  {
    "SongID": 1274725,
    "Position": 43
  },
  {
    "SongID": 1274748,
    "Position": 44
  },
  {
    "SongID": 1274740,
    "Position": 45
  },
  {
    "SongID": 1274799550,
    "Position": 46
  },
  {
    "SongID": 1274806782,
    "Position": 47
  },
  {
    "SongID": 972106,
    "Position": 48
  },
  {
    "SongID": 1272648,
    "Position": 49
  },
  {
    "SongID": 1274806781,
    "Position": 50
  },
  {
    "SongID": 1295928,
    "Position": 51
  },
  {
    "SongID": 1274806791,
    "Position": 52
  },
  {
    "SongID": 6567,
    "Position": 53
  },
  {
    "SongID": 1274806784,
    "Position": 54
  },
  {
    "SongID": 1274799555,
    "Position": 55
  },
  {
    "SongID": 1274806788,
    "Position": 56
  },
  {
    "SongID": 1274798767,
    "Position": 57
  },
  {
    "SongID": 1274799735,
    "Position": 58
  },
  {
    "SongID": 1274806786,
    "Position": 59
  },
  {
    "SongID": 1274799556,
    "Position": 60
  },
  {
    "SongID": 560128,
    "Position": 61
  },
  {
    "SongID": 1274806783,
    "Position": 62
  },
  {
    "SongID": 44547,
    "Position": 63
  },
  {
    "SongID": 1274274,
    "Position": 64
  },
  {
    "SongID": 21984,
    "Position": 65
  },
  {
    "SongID": 164882,
    "Position": 66
  },
  {
    "SongID": 1274806785,
    "Position": 68
  },
  {
    "SongID": 1274803149,
    "Position": 69
  },
  {
    "SongID": 1274753,
    "Position": 70
  },
  {
    "SongID": 1274806789,
    "Position": 71
  },
  {
    "SongID": 1274799563,
    "Position": 72
  },
  {
    "SongID": 1274802544,
    "Position": 73
  },
  {
    "SongID": 13290,
    "Position": 74
  },
  {
    "SongID": 1293895,
    "Position": 75
  },
  {
    "SongID": 1274799560,
    "Position": 76
  },
  {
    "SongID": 1446,
    "Position": 77
  },
  {
    "SongID": 1274806792,
    "Position": 78
  },
  {
    "SongID": 1274806793,
    "Position": 79
  },
  {
    "SongID": 1274806794,
    "Position": 80
  },
  {
    "SongID": 153799,
    "Position": 81
  },
  {
    "SongID": 164864,
    "Position": 82
  },
  {
    "SongID": 1274806796,
    "Position": 83
  },
  {
    "SongID": 164909,
    "Position": 84
  },
  {
    "SongID": 164860,
    "Position": 85
  },
  {
    "SongID": 165235,
    "Position": 86
  },
  {
    "SongID": 1274806790,
    "Position": 87
  },
  {
    "SongID": 1274806800,
    "Position": 88
  },
  {
    "SongID": 1274806799,
    "Position": 89
  },
  {
    "SongID": 1274800833,
    "Position": 90
  },
  {
    "SongID": 1274799554,
    "Position": 91
  },
  {
    "SongID": 164856,
    "Position": 92
  },
  {
    "SongID": 5301,
    "Position": 93
  },
  {
    "SongID": 1274799559,
    "Position": 94
  },
  {
    "SongID": 1274798766,
    "Position": 95
  },
  {
    "SongID": 1274806804,
    "Position": 96
  },
  {
    "SongID": 1274806803,
    "Position": 97
  },
  {
    "SongID": 1274799734,
    "Position": 98
  },
  {
    "SongID": 1274806808,
    "Position": 99
  },
  {
    "SongID": 1274800832,
    "Position": 101
  },
  {
    "SongID": 560150,
    "Position": 102
  },
  {
    "SongID": 15284,
    "Position": 103
  },
  {
    "SongID": 153804,
    "Position": 104
  },
  {
    "SongID": 1274806809,
    "Position": 105
  },
  {
    "SongID": 1288437,
    "Position": 106
  },
  {
    "SongID": 1274806807,
    "Position": 107
  },
  {
    "SongID": 1274803449,
    "Position": 108
  },
  {
    "SongID": 164862,
    "Position": 109
  },
  {
    "SongID": 1274805517,
    "Position": 110
  },
  {
    "SongID": 1274806806,
    "Position": 111
  },
  {
    "SongID": 1279363,
    "Position": 112
  },
  {
    "SongID": 1162363,
    "Position": 113
  },
  {
    "SongID": 1274735,
    "Position": 114
  },
  {
    "SongID": 1274806812,
    "Position": 115
  },
  {
    "SongID": 1274806831,
    "Position": 116
  },
  {
    "SongID": 1274798768,
    "Position": 117
  },
  {
    "SongID": 1274806826,
    "Position": 118
  },
  {
    "SongID": 1274806805,
    "Position": 119
  },
  {
    "SongID": 19354,
    "Position": 120
  },
  {
    "SongID": 1289914,
    "Position": 121
  },
  {
    "SongID": 1274806817,
    "Position": 122
  },
  {
    "SongID": 75,
    "Position": 123
  },
  {
    "SongID": 1293788,
    "Position": 124
  },
  {
    "SongID": 1277703,
    "Position": 125
  },
  {
    "SongID": 1274804339,
    "Position": 126
  },
  {
    "SongID": 1274803450,
    "Position": 128
  },
  {
    "SongID": 1274799673,
    "Position": 129
  },
  {
    "SongID": 1274806820,
    "Position": 130
  },
  {
    "SongID": 1274806821,
    "Position": 131
  },
  {
    "SongID": 1274806828,
    "Position": 132
  },
  {
    "SongID": 1274806813,
    "Position": 133
  },
  {
    "SongID": 165020,
    "Position": 134
  },
  {
    "SongID": 1274806824,
    "Position": 135
  },
  {
    "SongID": 17102,
    "Position": 136
  },
  {
    "SongID": 1274806814,
    "Position": 137
  },
  {
    "SongID": 164968,
    "Position": 138
  },
  {
    "SongID": 164854,
    "Position": 139
  },
  {
    "SongID": 1274806819,
    "Position": 140
  },
  {
    "SongID": 1274806841,
    "Position": 141
  },
  {
    "SongID": 164978,
    "Position": 142
  },
  {
    "SongID": 165143,
    "Position": 143
  },
  {
    "SongID": 1274806833,
    "Position": 144
  },
  {
    "SongID": 600127,
    "Position": 145
  },
  {
    "SongID": 1274804243,
    "Position": 146
  },
  {
    "SongID": 154160,
    "Position": 147
  },
  {
    "SongID": 502302,
    "Position": 148
  },
  {
    "SongID": 1274800834,
    "Position": 149
  },
  {
    "SongID": 1687,
    "Position": 150
  },
  {
    "SongID": 1274731,
    "Position": 151
  },
  {
    "SongID": 1274806815,
    "Position": 152
  },
  {
    "SongID": 1239704,
    "Position": 153
  },
  {
    "SongID": 1274806835,
    "Position": 154
  },
  {
    "SongID": 3715,
    "Position": 155
  },
  {
    "SongID": 1274806829,
    "Position": 157
  },
  {
    "SongID": 1274802033,
    "Position": 158
  },
  {
    "SongID": 1274806837,
    "Position": 159
  },
  {
    "SongID": 1295712,
    "Position": 160
  },
  {
    "SongID": 1274799557,
    "Position": 161
  },
  {
    "SongID": 164941,
    "Position": 162
  },
  {
    "SongID": 544042,
    "Position": 163
  },
  {
    "SongID": 1274806825,
    "Position": 165
  },
  {
    "SongID": 1274804340,
    "Position": 166
  },
  {
    "SongID": 165060,
    "Position": 167
  },
  {
    "SongID": 1228506,
    "Position": 168
  },
  {
    "SongID": 14536,
    "Position": 169
  },
  {
    "SongID": 1272654,
    "Position": 170
  },
  {
    "SongID": 108652,
    "Position": 171
  },
  {
    "SongID": 234113,
    "Position": 172
  },
  {
    "SongID": 1274798377,
    "Position": 174
  },
  {
    "SongID": 233914,
    "Position": 175
  },
  {
    "SongID": 1274807891,
    "Position": 176
  },
  {
    "SongID": 1274806830,
    "Position": 178
  },
  {
    "SongID": 164893,
    "Position": 179
  },
  {
    "SongID": 1274820492,
    "Position": 180
  },
  {
    "SongID": 1274806811,
    "Position": 181
  },
  {
    "SongID": 1274806822,
    "Position": 182
  },
  {
    "SongID": 25081,
    "Position": 183
  },
  {
    "SongID": 972112,
    "Position": 184
  },
  {
    "SongID": 234078,
    "Position": 186
  },
  {
    "SongID": 164942,
    "Position": 187
  },
  {
    "SongID": 1274806840,
    "Position": 189
  },
  {
    "SongID": 1274799737,
    "Position": 190
  },
  {
    "SongID": 1274807892,
    "Position": 191
  },
  {
    "SongID": 14014,
    "Position": 192
  },
  {
    "SongID": 1274801803,
    "Position": 193
  },
  {
    "SongID": 723442,
    "Position": 194
  },
  {
    "SongID": 1274806827,
    "Position": 195
  },
  {
    "SongID": 1274806798,
    "Position": 196
  },
  {
    "SongID": 1228569,
    "Position": 197
  },
  {
    "SongID": 1274806795,
    "Position": 198
  },
  {
    "SongID": 1274806836,
    "Position": 199
  }
]