[
    {
        "SongID": 124,
        "Position": 81
    },
    {
        "SongID": 304,
        "Position": 80
    },
    {
        "SongID": 1433,
        "Position": 67
    },
    {
        "SongID": 1642,
        "Position": 29
    },
    {
        "SongID": 5115,
        "Position": 70
    },
    {
        "SongID": 5831,
        "Position": 87
    },
    {
        "SongID": 8930,
        "Position": 57
    },
    {
        "SongID": 8979,
        "Position": 24
    },
    {
        "SongID": 11148,
        "Position": 50
    },
    {
        "SongID": 12106,
        "Position": 64
    },
    {
        "SongID": 12281,
        "Position": 95
    },
    {
        "SongID": 12959,
        "Position": 42
    },
    {
        "SongID": 15931,
        "Position": 65
    },
    {
        "SongID": 31572,
        "Position": 53
    },
    {
        "SongID": 34661,
        "Position": 11
    },
    {
        "SongID": 118993,
        "Position": 8
    },
    {
        "SongID": 145583,
        "Position": 85
    },
    {
        "SongID": 149011,
        "Position": 71
    },
    {
        "SongID": 168575,
        "Position": 14
    },
    {
        "SongID": 168582,
        "Position": 93
    },
    {
        "SongID": 168587,
        "Position": 17
    },
    {
        "SongID": 168622,
        "Position": 3
    },
    {
        "SongID": 168634,
        "Position": 62
    },
    {
        "SongID": 168646,
        "Position": 7
    },
    {
        "SongID": 168688,
        "Position": 72
    },
    {
        "SongID": 199873,
        "Position": 98
    },
    {
        "SongID": 203712,
        "Position": 89
    },
    {
        "SongID": 534055,
        "Position": 49
    },
    {
        "SongID": 536082,
        "Position": 9
    },
    {
        "SongID": 536106,
        "Position": 45
    },
    {
        "SongID": 539596,
        "Position": 2
    },
    {
        "SongID": 539647,
        "Position": 39
    },
    {
        "SongID": 540572,
        "Position": 43
    },
    {
        "SongID": 600357,
        "Position": 69
    },
    {
        "SongID": 603727,
        "Position": 94
    },
    {
        "SongID": 604417,
        "Position": 88
    },
    {
        "SongID": 605474,
        "Position": 75
    },
    {
        "SongID": 618362,
        "Position": 18
    },
    {
        "SongID": 724120,
        "Position": 47
    },
    {
        "SongID": 725030,
        "Position": 44
    },
    {
        "SongID": 816317,
        "Position": 36
    },
    {
        "SongID": 816541,
        "Position": 27
    },
    {
        "SongID": 816877,
        "Position": 96
    },
    {
        "SongID": 916844,
        "Position": 41
    },
    {
        "SongID": 947375,
        "Position": 77
    },
    {
        "SongID": 1003543,
        "Position": 86
    },
    {
        "SongID": 1019911,
        "Position": 68
    },
    {
        "SongID": 1036856,
        "Position": 5
    },
    {
        "SongID": 1080169,
        "Position": 92
    },
    {
        "SongID": 1177155,
        "Position": 59
    },
    {
        "SongID": 1194317,
        "Position": 52
    },
    {
        "SongID": 1194627,
        "Position": 21
    },
    {
        "SongID": 1227472,
        "Position": 46
    },
    {
        "SongID": 1227592,
        "Position": 15
    },
    {
        "SongID": 1228113,
        "Position": 60
    },
    {
        "SongID": 1228166,
        "Position": 22
    },
    {
        "SongID": 1228167,
        "Position": 19
    },
    {
        "SongID": 1228172,
        "Position": 13
    },
    {
        "SongID": 1228175,
        "Position": 79
    },
    {
        "SongID": 1228177,
        "Position": 16
    },
    {
        "SongID": 1228178,
        "Position": 66
    },
    {
        "SongID": 1228192,
        "Position": 73
    },
    {
        "SongID": 1228199,
        "Position": 34
    },
    {
        "SongID": 1228235,
        "Position": 56
    },
    {
        "SongID": 1228255,
        "Position": 90
    },
    {
        "SongID": 1230179,
        "Position": 97
    },
    {
        "SongID": 1230338,
        "Position": 26
    },
    {
        "SongID": 1230378,
        "Position": 33
    },
    {
        "SongID": 1232019,
        "Position": 54
    },
    {
        "SongID": 1233468,
        "Position": 82
    },
    {
        "SongID": 1233483,
        "Position": 20
    },
    {
        "SongID": 1234937,
        "Position": 4
    },
    {
        "SongID": 1237667,
        "Position": 25
    },
    {
        "SongID": 1237900,
        "Position": 35
    },
    {
        "SongID": 1239116,
        "Position": 55
    },
    {
        "SongID": 1239704,
        "Position": 76
    },
    {
        "SongID": 1241609,
        "Position": 63
    },
    {
        "SongID": 1241698,
        "Position": 37
    },
    {
        "SongID": 1242027,
        "Position": 38
    },
    {
        "SongID": 1242647,
        "Position": 99
    },
    {
        "SongID": 1243940,
        "Position": 100
    },
    {
        "SongID": 1244687,
        "Position": 32
    },
    {
        "SongID": 1244698,
        "Position": 30
    },
    {
        "SongID": 1244766,
        "Position": 58
    },
    {
        "SongID": 1245016,
        "Position": 10
    },
    {
        "SongID": 1245436,
        "Position": 40
    },
    {
        "SongID": 1246503,
        "Position": 1
    },
    {
        "SongID": 1246650,
        "Position": 91
    },
    {
        "SongID": 1246774,
        "Position": 6
    },
    {
        "SongID": 1247503,
        "Position": 48
    },
    {
        "SongID": 1247654,
        "Position": 78
    },
    {
        "SongID": 1247691,
        "Position": 83
    },
    {
        "SongID": 1247692,
        "Position": 84
    },
    {
        "SongID": 1247695,
        "Position": 31
    },
    {
        "SongID": 1247696,
        "Position": 61
    },
    {
        "SongID": 1247722,
        "Position": 12
    },
    {
        "SongID": 1247900,
        "Position": 23
    },
    {
        "SongID": 1247901,
        "Position": 28
    },
    {
        "SongID": 1247902,
        "Position": 51
    },
    {
        "SongID": 1247903,
        "Position": 74
    }
]