[
    {
        "SongID": 1295449,
        "Position": 1
    },
    {
        "SongID": 1295450,
        "Position": 2
    },
    {
        "SongID": 1295457,
        "Position": 3
    },
    {
        "SongID": 1294971,
        "Position": 4
    },
    {
        "SongID": 1295452,
        "Position": 5
    },
    {
        "SongID": 1295454,
        "Position": 6
    },
    {
        "SongID": 1295451,
        "Position": 7
    },
    {
        "SongID": 1295456,
        "Position": 8
    },
    {
        "SongID": 1295453,
        "Position": 9
    },
    {
        "SongID": 1295460,
        "Position": 10
    },
    {
        "SongID": 1295455,
        "Position": 11
    },
    {
        "SongID": 1294966,
        "Position": 12
    },
    {
        "SongID": 1295458,
        "Position": 13
    },
    {
        "SongID": 1295459,
        "Position": 14
    },
    {
        "SongID": 1295463,
        "Position": 15
    },
    {
        "SongID": 1295464,
        "Position": 16
    },
    {
        "SongID": 1295462,
        "Position": 17
    },
    {
        "SongID": 1295461,
        "Position": 18
    },
    {
        "SongID": 1294967,
        "Position": 19
    },
    {
        "SongID": 1294969,
        "Position": 20
    },
    {
        "SongID": 1288546,
        "Position": 21
    },
    {
        "SongID": 1295465,
        "Position": 22
    },
    {
        "SongID": 1274467,
        "Position": 23
    },
    {
        "SongID": 1274494,
        "Position": 24
    },
    {
        "SongID": 1248496,
        "Position": 25
    },
    {
        "SongID": 1294958,
        "Position": 26
    },
    {
        "SongID": 1272717,
        "Position": 27
    },
    {
        "SongID": 1272716,
        "Position": 28
    },
    {
        "SongID": 118677,
        "Position": 29
    },
    {
        "SongID": 1274514,
        "Position": 30
    },
    {
        "SongID": 1227291,
        "Position": 31
    },
    {
        "SongID": 1295389,
        "Position": 32
    },
    {
        "SongID": 1227274,
        "Position": 33
    },
    {
        "SongID": 1289872,
        "Position": 34
    },
    {
        "SongID": 1272713,
        "Position": 35
    },
    {
        "SongID": 1274468,
        "Position": 36
    },
    {
        "SongID": 1294960,
        "Position": 37
    },
    {
        "SongID": 1280306,
        "Position": 38
    },
    {
        "SongID": 1274500,
        "Position": 39
    },
    {
        "SongID": 1274449,
        "Position": 40
    },
    {
        "SongID": 1287705,
        "Position": 41
    },
    {
        "SongID": 1168762,
        "Position": 42
    },
    {
        "SongID": 34985,
        "Position": 43
    },
    {
        "SongID": 1293405,
        "Position": 44
    },
    {
        "SongID": 34988,
        "Position": 45
    },
    {
        "SongID": 1294962,
        "Position": 46
    },
    {
        "SongID": 229698,
        "Position": 47
    },
    {
        "SongID": 1288547,
        "Position": 48
    },
    {
        "SongID": 1274447,
        "Position": 49
    },
    {
        "SongID": 1291345,
        "Position": 50
    },
    {
        "SongID": 1294961,
        "Position": 51
    },
    {
        "SongID": 605518,
        "Position": 52
    },
    {
        "SongID": 1294963,
        "Position": 53
    },
    {
        "SongID": 1227287,
        "Position": 54
    },
    {
        "SongID": 1272690,
        "Position": 55
    },
    {
        "SongID": 229644,
        "Position": 56
    },
    {
        "SongID": 1274442,
        "Position": 57
    },
    {
        "SongID": 601640,
        "Position": 58
    },
    {
        "SongID": 14969,
        "Position": 59
    },
    {
        "SongID": 1274460,
        "Position": 60
    },
    {
        "SongID": 1294959,
        "Position": 61
    },
    {
        "SongID": 1227271,
        "Position": 62
    },
    {
        "SongID": 229593,
        "Position": 63
    },
    {
        "SongID": 34982,
        "Position": 64
    },
    {
        "SongID": 1274515,
        "Position": 65
    },
    {
        "SongID": 1274466,
        "Position": 66
    },
    {
        "SongID": 34987,
        "Position": 67
    },
    {
        "SongID": 1236278,
        "Position": 68
    },
    {
        "SongID": 1272684,
        "Position": 69
    },
    {
        "SongID": 229465,
        "Position": 70
    },
    {
        "SongID": 1281327,
        "Position": 71
    },
    {
        "SongID": 23551,
        "Position": 72
    },
    {
        "SongID": 1235610,
        "Position": 73
    },
    {
        "SongID": 1277731,
        "Position": 74
    },
    {
        "SongID": 948814,
        "Position": 75
    },
    {
        "SongID": 1272678,
        "Position": 76
    },
    {
        "SongID": 1248495,
        "Position": 77
    },
    {
        "SongID": 229580,
        "Position": 78
    },
    {
        "SongID": 35240,
        "Position": 79
    },
    {
        "SongID": 1273438,
        "Position": 80
    },
    {
        "SongID": 1272627,
        "Position": 81
    },
    {
        "SongID": 1274458,
        "Position": 82
    },
    {
        "SongID": 1274490,
        "Position": 83
    },
    {
        "SongID": 229520,
        "Position": 84
    },
    {
        "SongID": 1294964,
        "Position": 85
    },
    {
        "SongID": 1284247,
        "Position": 86
    },
    {
        "SongID": 229605,
        "Position": 87
    },
    {
        "SongID": 229783,
        "Position": 88
    },
    {
        "SongID": 1274471,
        "Position": 89
    },
    {
        "SongID": 604101,
        "Position": 90
    },
    {
        "SongID": 535073,
        "Position": 91
    },
    {
        "SongID": 1274469,
        "Position": 92
    },
    {
        "SongID": 229560,
        "Position": 93
    },
    {
        "SongID": 21983,
        "Position": 94
    },
    {
        "SongID": 604103,
        "Position": 95
    },
    {
        "SongID": 229631,
        "Position": 96
    },
    {
        "SongID": 1274484,
        "Position": 97
    },
    {
        "SongID": 229588,
        "Position": 98
    },
    {
        "SongID": 230264,
        "Position": 99
    },
    {
        "SongID": 604102,
        "Position": 100
    },
    {
        "SongID": 1260637,
        "Position": 101
    },
    {
        "SongID": 229494,
        "Position": 102
    },
    {
        "SongID": 1246159,
        "Position": 103
    },
    {
        "SongID": 229478,
        "Position": 104
    },
    {
        "SongID": 24320,
        "Position": 105
    },
    {
        "SongID": 1274450,
        "Position": 106
    },
    {
        "SongID": 1272719,
        "Position": 107
    },
    {
        "SongID": 535062,
        "Position": 108
    },
    {
        "SongID": 605519,
        "Position": 109
    },
    {
        "SongID": 604096,
        "Position": 110
    },
    {
        "SongID": 723380,
        "Position": 111
    },
    {
        "SongID": 1270398,
        "Position": 112
    },
    {
        "SongID": 229488,
        "Position": 113
    },
    {
        "SongID": 229452,
        "Position": 114
    },
    {
        "SongID": 229501,
        "Position": 115
    },
    {
        "SongID": 604094,
        "Position": 116
    },
    {
        "SongID": 229583,
        "Position": 117
    },
    {
        "SongID": 611433,
        "Position": 118
    },
    {
        "SongID": 605520,
        "Position": 119
    },
    {
        "SongID": 229705,
        "Position": 120
    },
    {
        "SongID": 1274473,
        "Position": 121
    },
    {
        "SongID": 1258475,
        "Position": 122
    },
    {
        "SongID": 229636,
        "Position": 123
    },
    {
        "SongID": 1272666,
        "Position": 124
    },
    {
        "SongID": 160362,
        "Position": 125
    },
    {
        "SongID": 21982,
        "Position": 126
    },
    {
        "SongID": 604106,
        "Position": 127
    },
    {
        "SongID": 229656,
        "Position": 128
    },
    {
        "SongID": 604098,
        "Position": 129
    },
    {
        "SongID": 1274437,
        "Position": 130
    },
    {
        "SongID": 25926,
        "Position": 131
    },
    {
        "SongID": 1294968,
        "Position": 132
    },
    {
        "SongID": 35974,
        "Position": 133
    },
    {
        "SongID": 23548,
        "Position": 134
    },
    {
        "SongID": 23550,
        "Position": 135
    },
    {
        "SongID": 1272927,
        "Position": 136
    },
    {
        "SongID": 229901,
        "Position": 137
    },
    {
        "SongID": 1293412,
        "Position": 138
    },
    {
        "SongID": 1284242,
        "Position": 139
    },
    {
        "SongID": 1270393,
        "Position": 140
    },
    {
        "SongID": 229802,
        "Position": 141
    },
    {
        "SongID": 1272714,
        "Position": 142
    },
    {
        "SongID": 1246621,
        "Position": 143
    },
    {
        "SongID": 22826,
        "Position": 144
    },
    {
        "SongID": 31713,
        "Position": 145
    },
    {
        "SongID": 119666,
        "Position": 146
    },
    {
        "SongID": 229924,
        "Position": 147
    },
    {
        "SongID": 1163447,
        "Position": 148
    },
    {
        "SongID": 229453,
        "Position": 149
    },
    {
        "SongID": 23549,
        "Position": 150
    },
    {
        "SongID": 601429,
        "Position": 151
    },
    {
        "SongID": 1272648,
        "Position": 152
    },
    {
        "SongID": 39,
        "Position": 153
    },
    {
        "SongID": 1286167,
        "Position": 154
    },
    {
        "SongID": 229456,
        "Position": 155
    },
    {
        "SongID": 1288574,
        "Position": 156
    },
    {
        "SongID": 1246158,
        "Position": 157
    },
    {
        "SongID": 539840,
        "Position": 158
    },
    {
        "SongID": 1020040,
        "Position": 159
    },
    {
        "SongID": 601426,
        "Position": 160
    },
    {
        "SongID": 535138,
        "Position": 161
    },
    {
        "SongID": 230192,
        "Position": 162
    },
    {
        "SongID": 1270392,
        "Position": 163
    },
    {
        "SongID": 1250124,
        "Position": 164
    },
    {
        "SongID": 1593,
        "Position": 165
    },
    {
        "SongID": 23553,
        "Position": 166
    },
    {
        "SongID": 229491,
        "Position": 167
    },
    {
        "SongID": 1270394,
        "Position": 168
    },
    {
        "SongID": 1274472,
        "Position": 169
    },
    {
        "SongID": 1269856,
        "Position": 170
    },
    {
        "SongID": 229930,
        "Position": 171
    },
    {
        "SongID": 229519,
        "Position": 172
    },
    {
        "SongID": 229466,
        "Position": 173
    },
    {
        "SongID": 1288545,
        "Position": 174
    },
    {
        "SongID": 1274462,
        "Position": 175
    },
    {
        "SongID": 229667,
        "Position": 176
    },
    {
        "SongID": 1270396,
        "Position": 177
    },
    {
        "SongID": 229510,
        "Position": 178
    },
    {
        "SongID": 229846,
        "Position": 179
    },
    {
        "SongID": 1287686,
        "Position": 180
    },
    {
        "SongID": 229470,
        "Position": 181
    },
    {
        "SongID": 754914,
        "Position": 182
    },
    {
        "SongID": 1284244,
        "Position": 183
    },
    {
        "SongID": 1272691,
        "Position": 184
    },
    {
        "SongID": 229918,
        "Position": 185
    },
    {
        "SongID": 1260638,
        "Position": 186
    },
    {
        "SongID": 1230445,
        "Position": 187
    },
    {
        "SongID": 1272931,
        "Position": 188
    },
    {
        "SongID": 21258,
        "Position": 189
    },
    {
        "SongID": 229877,
        "Position": 190
    },
    {
        "SongID": 1294965,
        "Position": 191
    },
    {
        "SongID": 1290721,
        "Position": 192
    },
    {
        "SongID": 1294973,
        "Position": 193
    },
    {
        "SongID": 12606,
        "Position": 194
    },
    {
        "SongID": 229766,
        "Position": 195
    },
    {
        "SongID": 229706,
        "Position": 196
    },
    {
        "SongID": 1280020,
        "Position": 197
    },
    {
        "SongID": 539290,
        "Position": 198
    },
    {
        "SongID": 229451,
        "Position": 199
    },
    {
        "SongID": 1278665,
        "Position": 200
    }
]