[
  {
    "SongID": "1295428",
    "Title": "Не ме занимавай",
    "Artist": "VANE$$A"
  },
  {
    "SongID": "1295429",
    "Title": "Aww Tú Ve",
    "Artist": "Donaty & Michael Flores"
  },
  {
    "SongID": "1295430",
    "Title": "Nunca Te Detenga",
    "Artist": "Santos Angel Arias, RONNY GTA & Megadivo produce"
  },
  {
    "SongID": "1295431",
    "Title": "فين يوجعك",
    "Artist": "Ahmad Amer"
  },
  {
    "SongID": "1295432",
    "Title": "Dis-moi oui",
    "Artist": "SANTA"
  },
  {
    "SongID": "1295433",
    "Title": "PISTEPSE ME",
    "Artist": "Strat & BeTaf Beats"
  },
  {
    "SongID": "1295434",
    "Title": "To Ftoxiko Mou",
    "Artist": "FANN & Hades"
  },
  {
    "SongID": "1295435",
    "Title": "Poioi",
    "Artist": "FANN, Dani Gambino & Hades"
  },
  {
    "SongID": "1295436",
    "Title": "Irtha Bam",
    "Artist": "FANN & Greco Beats"
  },
  {
    "SongID": "1295437",
    "Title": "To Teleutaio",
    "Artist": "FANN, Bloody Hawk & Hades"
  },
  {
    "SongID": "1295438",
    "Title": "Apo To Tipota",
    "Artist": "FANN & Hades"
  },
  {
    "SongID": "1295439",
    "Title": "Fann Is Back",
    "Artist": "FANN & Greco Beats"
  },
  {
    "SongID": "1295440",
    "Title": "Asteria",
    "Artist": "FANN, CARLA & Greco Beats"
  },
  {
    "SongID": "1295441",
    "Title": "Paranoia",
    "Artist": "FANN & Greco Beats"
  },
  {
    "SongID": "1295442",
    "Title": "Stagones (Bonus Track)",
    "Artist": "FANN & Hades"
  },
  {
    "SongID": "1295443",
    "Title": "American Obituary",
    "Artist": "U2"
  },
  {
    "SongID": "1295444",
    "Title": "The Tears Of Things",
    "Artist": "U2"
  },
  {
    "SongID": "1295445",
    "Title": "Song Of The Future",
    "Artist": "U2"
  },
  {
    "SongID": "1295446",
    "Title": "Yours Eternally (feat. Ed Sheeran & Taras Topolia)",
    "Artist": "U2"
  },
  {
    "SongID": "1295447",
    "Title": "One Life At A Time",
    "Artist": "U2"
  },
  {
    "SongID": "1295448",
    "Title": "Wildpeace",
    "Artist": "U2, Jacknife Lee & Adeola"
  },
  {
    "SongID": "1295449",
    "Title": "משפחה וכבוד",
    "Artist": "Omer Adam"
  },
  {
    "SongID": "1295450",
    "Title": "פלאזה אתנה",
    "Artist": "Omer Adam"
  },
  {
    "SongID": "1295451",
    "Title": "אלבי",
    "Artist": "Omer Adam"
  },
  {
    "SongID": "1295452",
    "Title": "אורות כחולים",
    "Artist": "Omer Adam"
  },
  {
    "SongID": "1295453",
    "Title": "יש יותר מדי שירים היום",
    "Artist": "Omer Adam"
  },
  {
    "SongID": "1295454",
    "Title": "לילות יפים",
    "Artist": "Omer Adam, Gal Adam & Roei Adam"
  },
  {
    "SongID": "1295455",
    "Title": "שירתו של החורף",
    "Artist": "Omer Adam"
  },
  {
    "SongID": "1295456",
    "Title": "פינה של שקט",
    "Artist": "Omer Adam"
  },
  {
    "SongID": "1295457",
    "Title": "בן 32",
    "Artist": "Omer Adam"
  },
  {
    "SongID": "1295458",
    "Title": "מישהו שמזכיר אותי",
    "Artist": "Omer Adam"
  },
  {
    "SongID": "1295459",
    "Title": "ריו דה ז'נרו",
    "Artist": "Omer Adam"
  },
  {
    "SongID": "1295460",
    "Title": "תקופה חרא",
    "Artist": "Omer Adam"
  },
  {
    "SongID": "1295461",
    "Title": "מאפיה",
    "Artist": "Omer Adam"
  },
  {
    "SongID": "1295462",
    "Title": "הסוף הזה",
    "Artist": "Omer Adam"
  },
  {
    "SongID": "1295463",
    "Title": "להינשא הלילה (רצועת בונוס)",
    "Artist": "Omer Adam"
  },
  {
    "SongID": "1295464",
    "Title": "להשתטות (רצועת בונוס)",
    "Artist": "Omer Adam"
  },
  {
    "SongID": "1295465",
    "Title": "אבא אבא אבא",
    "Artist": "Omer Adam"
  },
  {
    "SongID": "1295466",
    "Title": "Mutta Kalakki (From \"Youth\")",
    "Artist": "G.V. Prakash Kumar & Ken Karunaas"
  },
  {
    "SongID": "1295467",
    "Title": "The Rain",
    "Artist": "G. Valas"
  },
  {
    "SongID": "1295468",
    "Title": "Old World",
    "Artist": "Mino Srso"
  },
  {
    "SongID": "1295469",
    "Title": "panacea  (2)",
    "Artist": "Laiqa H."
  },
  {
    "SongID": "1295470",
    "Title": "Fallen World",
    "Artist": "Zed Halaj"
  },
  {
    "SongID": "1295471",
    "Title": "Black Summer",
    "Artist": "Virgil Tetamonte"
  },
  {
    "SongID": "1295472",
    "Title": "Pale Streetlight",
    "Artist": "Fakerest"
  },
  {
    "SongID": "1295473",
    "Title": "Ichibyo",
    "Artist": "SixTONES"
  },
  {
    "SongID": "1295474",
    "Title": "Crescendo",
    "Artist": "M!LK"
  },
  {
    "SongID": "1295475",
    "Title": "? (물음표) [feat. 최자 & Zion.T]",
    "Artist": "프라이머리"
  },
  {
    "SongID": "1295476",
    "Title": "All of You",
    "Artist": "RIIZE"
  },
  {
    "SongID": "1295477",
    "Title": "Amin (Amen) [Live]",
    "Artist": "BBO"
  },
  {
    "SongID": "1295478",
    "Title": "Peter Parker (Balkanic Version)",
    "Artist": "Lele & Manele VTM"
  },
  {
    "SongID": "1295479",
    "Title": "Embrace (Ambient Sleep)",
    "Artist": "Crystalline Cove"
  },
  {
    "SongID": "1295480",
    "Title": "Pat Tha Ya (Pattaya)",
    "Artist": "MEYOU"
  },
  {
    "SongID": "1295481",
    "Title": "我的存在就是愛你",
    "Artist": "張惠妹"
  },
  {
    "SongID": "1295482",
    "Title": "8 диво",
    "Artist": "Артем Пивоваров"
  },
  {
    "SongID": "1295483",
    "Title": "Колись в мене була хлопців рота",
    "Artist": "ROMIX ST"
  },
  {
    "SongID": "1295484",
    "Title": "Love & War",
    "Artist": "Lil Poppa"
  },
  {
    "SongID": "1295485",
    "Title": "Escándalo",
    "Artist": "Ñengo Flow"
  },
  {
    "SongID": "1295486",
    "Title": "= (Equal Sign)",
    "Artist": "j-hope"
  },
  {
    "SongID": "1295487",
    "Title": "MAY KIN THANH DO",
    "Artist": "Richie D. ICY, Obito & T.O.Noise"
  },
  {
    "SongID": "1295488",
    "Title": "Nếu Như Anh Đến",
    "Artist": "Văn Mai Hương"
  }
]