[
    {
        "SongID": 925,
        "Position": 76
    },
    {
        "SongID": 1587,
        "Position": 65
    },
    {
        "SongID": 1725,
        "Position": 21
    },
    {
        "SongID": 1730,
        "Position": 30
    },
    {
        "SongID": 1903,
        "Position": 67
    },
    {
        "SongID": 2193,
        "Position": 100
    },
    {
        "SongID": 4103,
        "Position": 68
    },
    {
        "SongID": 4313,
        "Position": 11
    },
    {
        "SongID": 4905,
        "Position": 83
    },
    {
        "SongID": 12861,
        "Position": 92
    },
    {
        "SongID": 17271,
        "Position": 56
    },
    {
        "SongID": 21622,
        "Position": 35
    },
    {
        "SongID": 110170,
        "Position": 78
    },
    {
        "SongID": 185580,
        "Position": 15
    },
    {
        "SongID": 196458,
        "Position": 93
    },
    {
        "SongID": 202587,
        "Position": 54
    },
    {
        "SongID": 203686,
        "Position": 77
    },
    {
        "SongID": 215325,
        "Position": 95
    },
    {
        "SongID": 236187,
        "Position": 99
    },
    {
        "SongID": 236462,
        "Position": 66
    },
    {
        "SongID": 539596,
        "Position": 79
    },
    {
        "SongID": 539616,
        "Position": 63
    },
    {
        "SongID": 540572,
        "Position": 47
    },
    {
        "SongID": 542873,
        "Position": 5
    },
    {
        "SongID": 545257,
        "Position": 51
    },
    {
        "SongID": 563908,
        "Position": 45
    },
    {
        "SongID": 600516,
        "Position": 81
    },
    {
        "SongID": 603246,
        "Position": 53
    },
    {
        "SongID": 603250,
        "Position": 61
    },
    {
        "SongID": 603515,
        "Position": 91
    },
    {
        "SongID": 622394,
        "Position": 43
    },
    {
        "SongID": 725913,
        "Position": 60
    },
    {
        "SongID": 972992,
        "Position": 80
    },
    {
        "SongID": 974673,
        "Position": 50
    },
    {
        "SongID": 1011370,
        "Position": 4
    },
    {
        "SongID": 1053941,
        "Position": 23
    },
    {
        "SongID": 1168435,
        "Position": 13
    },
    {
        "SongID": 1226430,
        "Position": 16
    },
    {
        "SongID": 1228163,
        "Position": 44
    },
    {
        "SongID": 1228386,
        "Position": 62
    },
    {
        "SongID": 1231765,
        "Position": 1
    },
    {
        "SongID": 1231766,
        "Position": 49
    },
    {
        "SongID": 1232846,
        "Position": 72
    },
    {
        "SongID": 1232852,
        "Position": 37
    },
    {
        "SongID": 1238047,
        "Position": 59
    },
    {
        "SongID": 1239704,
        "Position": 34
    },
    {
        "SongID": 1241217,
        "Position": 3
    },
    {
        "SongID": 1242186,
        "Position": 2
    },
    {
        "SongID": 1242730,
        "Position": 9
    },
    {
        "SongID": 1243081,
        "Position": 7
    },
    {
        "SongID": 1247102,
        "Position": 55
    },
    {
        "SongID": 1247742,
        "Position": 73
    },
    {
        "SongID": 1247996,
        "Position": 8
    },
    {
        "SongID": 1249685,
        "Position": 38
    },
    {
        "SongID": 1258685,
        "Position": 64
    },
    {
        "SongID": 1258687,
        "Position": 14
    },
    {
        "SongID": 1258691,
        "Position": 33
    },
    {
        "SongID": 1258694,
        "Position": 39
    },
    {
        "SongID": 1258695,
        "Position": 46
    },
    {
        "SongID": 1258696,
        "Position": 19
    },
    {
        "SongID": 1258699,
        "Position": 22
    },
    {
        "SongID": 1258700,
        "Position": 20
    },
    {
        "SongID": 1258701,
        "Position": 6
    },
    {
        "SongID": 1258707,
        "Position": 85
    },
    {
        "SongID": 1261522,
        "Position": 70
    },
    {
        "SongID": 1261531,
        "Position": 48
    },
    {
        "SongID": 1261632,
        "Position": 89
    },
    {
        "SongID": 1264544,
        "Position": 27
    },
    {
        "SongID": 1264866,
        "Position": 18
    },
    {
        "SongID": 1264867,
        "Position": 24
    },
    {
        "SongID": 1264868,
        "Position": 26
    },
    {
        "SongID": 1264869,
        "Position": 32
    },
    {
        "SongID": 1264870,
        "Position": 28
    },
    {
        "SongID": 1264871,
        "Position": 52
    },
    {
        "SongID": 1264873,
        "Position": 17
    },
    {
        "SongID": 1264876,
        "Position": 75
    },
    {
        "SongID": 1264879,
        "Position": 25
    },
    {
        "SongID": 1264881,
        "Position": 90
    },
    {
        "SongID": 1264883,
        "Position": 10
    },
    {
        "SongID": 1264884,
        "Position": 58
    },
    {
        "SongID": 1264886,
        "Position": 31
    },
    {
        "SongID": 1264887,
        "Position": 42
    },
    {
        "SongID": 1265295,
        "Position": 12
    },
    {
        "SongID": 1265296,
        "Position": 29
    },
    {
        "SongID": 1265297,
        "Position": 36
    },
    {
        "SongID": 1265298,
        "Position": 40
    },
    {
        "SongID": 1265299,
        "Position": 41
    },
    {
        "SongID": 1265300,
        "Position": 57
    },
    {
        "SongID": 1265301,
        "Position": 69
    },
    {
        "SongID": 1265302,
        "Position": 71
    },
    {
        "SongID": 1265303,
        "Position": 74
    },
    {
        "SongID": 1265304,
        "Position": 82
    },
    {
        "SongID": 1265305,
        "Position": 84
    },
    {
        "SongID": 1265306,
        "Position": 86
    },
    {
        "SongID": 1265307,
        "Position": 87
    },
    {
        "SongID": 1265308,
        "Position": 88
    },
    {
        "SongID": 1265309,
        "Position": 94
    },
    {
        "SongID": 1265310,
        "Position": 96
    },
    {
        "SongID": 1265311,
        "Position": 97
    },
    {
        "SongID": 1265312,
        "Position": 98
    }
]